<?xml version="1.0" encoding="UTF-16"?><tree>

<tree text="12. Iddhividhaniddeso" action="cscd/e0102n.mul0.xml" target="text" />

<tree text="13. Abhiññāniddeso" action="cscd/e0102n.mul1.xml" target="text" />

<tree text="14. Khandhaniddeso" action="cscd/e0102n.mul2.xml" target="text" />

<tree text="15. Āyatanadhātuniddeso" action="cscd/e0102n.mul3.xml" target="text" />

<tree text="16. Indriyasaccaniddeso" action="cscd/e0102n.mul4.xml" target="text" />

<tree text="17. Paññābhūminiddeso" action="cscd/e0102n.mul5.xml" target="text" />

<tree text="18. Diṭṭhivisuddhiniddeso" action="cscd/e0102n.mul6.xml" target="text" />

<tree text="19. Kaṅkhāvitaraṇavisuddhiniddeso" action="cscd/e0102n.mul7.xml" target="text" />

<tree text="20. Maggāmaggañāṇadassanavisuddhiniddeso" action="cscd/e0102n.mul8.xml" target="text" />

<tree text="21. Paṭipadāñāṇadassanavisuddhiniddeso" action="cscd/e0102n.mul9.xml" target="text" />

<tree text="22. Ñāṇadassanavisuddhiniddeso" action="cscd/e0102n.mul10.xml" target="text" />

<tree text="23. Paññābhāvanānisaṃsaniddeso" action="cscd/e0102n.mul11.xml" target="text" /></tree>