<?xml version="1.0" encoding="UTF-16"?><tree>

<tree text="1. Mahāpadānasuttaṃ" action="cscd/s0102m.mul0.xml" target="text" />

<tree text="2. Mahānidānasuttaṃ" action="cscd/s0102m.mul1.xml" target="text" />

<tree text="3. Mahāparinibbānasuttaṃ" action="cscd/s0102m.mul2.xml" target="text" />

<tree text="4. Mahāsudassanasuttaṃ" action="cscd/s0102m.mul3.xml" target="text" />

<tree text="5. Janavasabhasuttaṃ" action="cscd/s0102m.mul4.xml" target="text" />

<tree text="6. Mahāgovindasuttaṃ" action="cscd/s0102m.mul5.xml" target="text" />

<tree text="7. Mahāsamayasuttaṃ" action="cscd/s0102m.mul6.xml" target="text" />

<tree text="8. Sakkapañhasuttaṃ" action="cscd/s0102m.mul7.xml" target="text" />

<tree text="9. Mahāsatipaṭṭhānasuttaṃ" action="cscd/s0102m.mul8.xml" target="text" />

<tree text="10. Pāyāsisuttaṃ" action="cscd/s0102m.mul9.xml" target="text" /></tree>