<?xml version="1.0" encoding="UTF-16"?><tree>

<tree text="5. Pācittiyakaṇḍaṃ" action="cscd/vin02a1.att0.xml" target="text" />

<tree text="6. Pāṭidesanīyakaṇḍaṃ" action="cscd/vin02a1.att1.xml" target="text" />

<tree text="7. Sekhiyakaṇḍaṃ" action="cscd/vin02a1.att2.xml" target="text" />

<tree text="8. Sattādhikaraṇasamathā" action="cscd/vin02a1.att3.xml" target="text" />

<tree text="1. Pārājikakaṇḍaṃ (bhikkhunīvibhaṅgavaṇṇanā)" action="cscd/vin02a1.att4.xml" target="text" />

<tree text="2. Saṅghādisesakaṇḍaṃ (bhikkhunīvibhaṅgavaṇṇanā)" action="cscd/vin02a1.att5.xml" target="text" />

<tree text="3. Nissaggiyakaṇḍaṃ (bhikkhunīvibhaṅgavaṇṇanā)" action="cscd/vin02a1.att6.xml" target="text" />

<tree text="4. Pācittiyakaṇḍaṃ (bhikkhunīvibhaṅgavaṇṇanā)" action="cscd/vin02a1.att7.xml" target="text" />

<tree text="5. Pāṭidesanīyakaṇḍaṃ (bhikkhunīvibhaṅgavaṇṇanā)" action="cscd/vin02a1.att8.xml" target="text" /></tree>