<?xml version="1.0" encoding="UTF-16"?><tree>

<tree text="Ganthārambhakathā" action="cscd/vin11t.nrf0.xml" target="text" />

<tree text="Bhikkhuvibhaṅgo" action="cscd/vin11t.nrf1.xml" target="text" />

<tree text="Pārājikakathā" action="cscd/vin11t.nrf2.xml" target="text" />

<tree text="Saṅghādisesakathāvaṇṇanā" action="cscd/vin11t.nrf3.xml" target="text" />

<tree text="Aniyatakathāvaṇṇanā" action="cscd/vin11t.nrf4.xml" target="text" />

<tree text="Nissaggiyakathāvaṇṇanā" action="cscd/vin11t.nrf5.xml" target="text" />

<tree text="Pācittiyakathāvaṇṇanā" action="cscd/vin11t.nrf6.xml" target="text" />

<tree text="Pāṭidesanīyakathāvaṇṇanā" action="cscd/vin11t.nrf7.xml" target="text" />

<tree text="Sekhiyakathāvaṇṇanā" action="cscd/vin11t.nrf8.xml" target="text" />

<tree text="Bhikkhunivibhaṅgo" action="cscd/vin11t.nrf9.xml" target="text" />

<tree text="Pārājikakathāvaṇṇanā" action="cscd/vin11t.nrf10.xml" target="text" />

<tree text="Saṅghādisesakathāvaṇṇanā" action="cscd/vin11t.nrf11.xml" target="text" />

<tree text="Nissaggiyakathāvaṇṇanā" action="cscd/vin11t.nrf12.xml" target="text" />

<tree text="Pācittiyakathāvaṇṇanā" action="cscd/vin11t.nrf13.xml" target="text" />

<tree text="Pāṭidesanīyakathāvaṇṇanā" action="cscd/vin11t.nrf14.xml" target="text" />

<tree text="Sikkhākaraṇīyakathāvaṇṇanā" action="cscd/vin11t.nrf15.xml" target="text" />

<tree text="Mahāvaggo" action="cscd/vin11t.nrf16.xml" target="text" />

<tree text="Pabbajjākathāvaṇṇanā" action="cscd/vin11t.nrf17.xml" target="text" />

<tree text="Uposathakkhandhakakathāvaṇṇanā" action="cscd/vin11t.nrf18.xml" target="text" />

<tree text="Vassūpanāyikakkhandhakakathāvaṇṇanā" action="cscd/vin11t.nrf19.xml" target="text" />

<tree text="Pavāraṇakkhandhakakathāvaṇṇanā" action="cscd/vin11t.nrf20.xml" target="text" />

<tree text="Cammakkhandhakakathāvaṇṇanā" action="cscd/vin11t.nrf21.xml" target="text" />

<tree text="Bhesajjakkhandhakakathāvaṇṇanā" action="cscd/vin11t.nrf22.xml" target="text" />

<tree text="Kathinakkhandhakakathāvaṇṇanā" action="cscd/vin11t.nrf23.xml" target="text" />

<tree text="Cīvarakkhandhakakathāvaṇṇanā" action="cscd/vin11t.nrf24.xml" target="text" />

<tree text="Cūḷavaggo" action="cscd/vin11t.nrf25.xml" target="text" />

<tree text="Pārivāsikakkhandhakakathāvaṇṇanā" action="cscd/vin11t.nrf26.xml" target="text" />

<tree text="Samathakkhandhakakathāvaṇṇanā" action="cscd/vin11t.nrf27.xml" target="text" />

<tree text="Khuddakavatthukkhandhakakathāvaṇṇanā" action="cscd/vin11t.nrf28.xml" target="text" />

<tree text="Senāsanakkhandhakakathāvaṇṇanā" action="cscd/vin11t.nrf29.xml" target="text" />

<tree text="Vattakkhandhakakathāvaṇṇanā" action="cscd/vin11t.nrf30.xml" target="text" />

<tree text="Bhikkhunikkhandhakakathāvaṇṇanā" action="cscd/vin11t.nrf31.xml" target="text" />

<tree text="Catubbidhakammakathāvaṇṇanā" action="cscd/vin11t.nrf32.xml" target="text" />

<tree text="Kammavipattikathāvaṇṇanā" action="cscd/vin11t.nrf33.xml" target="text" />

<tree text="Pakiṇṇakavinicchayakathāvaṇṇanā" action="cscd/vin11t.nrf34.xml" target="text" />

<tree text="Kammaṭṭhānavibhāvanāvidhānakathāvaṇṇanā" action="cscd/vin11t.nrf35.xml" target="text" />

<tree text="Uttaravinicchaya-ṭīkā" action="cscd/vin11t.nrf36.xml" target="text" />

<tree text="Mahāvibhaṅgasaṅgahakathāvaṇṇanā" action="cscd/vin11t.nrf37.xml" target="text" />

<tree text="Bhikkhunivibhaṅgo" action="cscd/vin11t.nrf38.xml" target="text" />

<tree text="Catuvipattikathāvaṇṇanā" action="cscd/vin11t.nrf39.xml" target="text" />

<tree text="Adhikaraṇapaccayakathāvaṇṇanā" action="cscd/vin11t.nrf40.xml" target="text" />

<tree text="Khandhakapucchākathāvaṇṇanā" action="cscd/vin11t.nrf41.xml" target="text" />

<tree text="Samuṭṭhānasīsakathāvaṇṇanā" action="cscd/vin11t.nrf42.xml" target="text" />

<tree text="Āpattisamuṭṭhānakathāvaṇṇanā" action="cscd/vin11t.nrf43.xml" target="text" />

<tree text="Ekuttaranayakathāvaṇṇanā" action="cscd/vin11t.nrf44.xml" target="text" />

<tree text="Sedamocanakathāvaṇṇanā" action="cscd/vin11t.nrf45.xml" target="text" />

<tree text="Sādhāraṇāsādhāraṇakathāvaṇṇanā" action="cscd/vin11t.nrf46.xml" target="text" />

<tree text="Lakkhaṇakathāvaṇṇanā" action="cscd/vin11t.nrf47.xml" target="text" />

<tree text="Sabbasaṅkalananayakathāvaṇṇanā" action="cscd/vin11t.nrf48.xml" target="text" /></tree>